testindex_knowledge_contract/__init__.py
testindex_knowledge_contract/bench_constants.py
testindex_knowledge_contract/neo4j_client.py
testindex_knowledge_contract/schema.py
testindex_knowledge_contract/test_data/gold_schema.json
testindex_knowledge_contract-0.1.0.dist-info/METADATA
testindex_knowledge_contract-0.1.0.dist-info/WHEEL
testindex_knowledge_contract-0.1.0.dist-info/top_level.txt
testindex_knowledge_contract-0.1.0.dist-info/RECORD
