Metadata-Version: 2.4
Name: testindex-knowledge-contract
Version: 0.1.0
Summary: Knowledge v1 Contract for TestIndex
Author: TestIndex Team
License: MIT
Requires-Python: >=3.8
Requires-Dist: neo4j<6.0.0,>=5.0.0
Dynamic: author
Dynamic: requires-python
